click_clack/ClickClack.py
click_clack/__init__.py
click_clack/click_clack.py
click_clack/crawl/__init__.py
click_clack/mcp/__init__.py
click_clack/mcp/generate_mcp_server.py
click_clack/utils/__init__.py
click_clack/utils/generate_help.py
click_clack-0.2.1.dist-info/METADATA
click_clack-0.2.1.dist-info/WHEEL
click_clack-0.2.1.dist-info/entry_points.txt
click_clack-0.2.1.dist-info/licenses/LICENSE
click_clack-0.2.1.dist-info/RECORD
