Metadata-Version: 2.4
Name: click-clack
Version: 0.2.1
Summary: Autogenerated MCP Server & UI for all of your Click commands.
Project-URL: Homepage, https://github.com/JasonSteving99/click-clack
Author-email: Jason Steving <jasonmail99@gmail.com>
License:                                  Apache License
License-File: LICENSE
Classifier: Development Status :: 3 - Alpha
Classifier: Intended Audience :: Developers
Classifier: License :: OSI Approved :: Apache Software License
Classifier: Programming Language :: Python :: 3 :: Only
Classifier: Programming Language :: Python :: 3.9
Classifier: Programming Language :: Python :: 3.10
Classifier: Programming Language :: Python :: 3.11
Classifier: Programming Language :: Python :: 3.12
Classifier: Topic :: Software Development :: User Interfaces
Requires-Python: >=3.10
Requires-Dist: asyncclick==8.1.*
Requires-Dist: click==8.1.*
Requires-Dist: marimo==0.11.*
Requires-Dist: mcp>=1.3.0
